fibonacci.v
module fibonacci #(
    parameter in_size  = 32,
    parameter out_size = 32
)
(
    input                 clk,
    input                 start, //synchronous negedge reset
    input  [in_size-1 :0] n,     //assumption n >= 1
    output                valid, //goes high when fib = F(n)
    output [out_size-1:0] fib    //outputs F(n), assuming F(n) can be contained within out_size bits
);
//n indicates the n-th Fibonacci F(n) number desired to be calculated.

reg [in_size-1 :0] n_count;
reg [out_size-1:0] f0;
reg [out_size-1:0] f1;
reg [out_size-1:0] fn;

//Output assignments
assign fib   = fn;
assign valid = (n_count==n);

//Negedge FF for f0
always @(negedge clk) begin
  if(~start) begin
    f0 <= 0; //F_0 begins at 0
  end else if(n_count == n) begin //prevents overflowing
    f0 <= f0;
  end else begin
    f0 <= f1;
  end
end

//Negedge FF for f1
always @(negedge clk) begin
  if(~start) begin
    f1 <= 1; //F_1 begins at 1
  end else if(n_count == n) begin //prevents overflowing
    f1 <= f1;
  end else begin
    f1 <= fn;
  end
end

//Posedge FF for fN
always @(posedge clk) begin
  if(~start) begin
    fn <= 1;
  end else if(n_count == n) begin //prevents overflowing
    fn <= fn;
  end else begin
    fn <= f0 + f1; //Fibonacci "next number" calculation 
  end   
end

//Posedge FF for n_count
always @(posedge clk, negedge start) begin
  if(~start) begin
    n_count <= 1; //Previously assumed n >= 1
  end else if(n_count==n) begin //prevents overflowing
    n_count <= n_count;
  end else begin
    n_count <= n_count + 1;
  end 
end

endmodule

tb_fibonacci.v
`timescale 1 ns /  100 ps
module tb_fibonacci ();

reg         clk, start;
reg  [31:0] n; 
wire        valid;
wire [31:0] fib;

fibonacci #(
  .in_size(32),
  .out_size(32)
)
f(
  .clk(clk),
  .start(start), 
  .n(n),     
  .valid(valid),
  .fib(fib)
);

always #10 clk = ~clk;

initial begin
  $dumpfile("fib.vcd");
  $dumpvars;
  $display ("Starting simulation.....");
  n = 10;
  start = 0;
  clk = 0;
  #10
  start = 1;
  #500
  $display ("Simulation Complete!");
  $finish;
end

endmodule

fib.vcd
$date
	Tue Dec  1 02:11:34 2020
$end
$version
	Icarus Verilog
$end
$timescale
	100ps
$end
$scope module tb_fibonacci $end
$var wire 1 ! valid $end
$var wire 32 " fib [31:0] $end
$var reg 1 # clk $end
$var reg 32 $ n [31:0] $end
$var reg 1 % start $end
$scope module f $end
$var wire 1 # clk $end
$var wire 32 & fib [31:0] $end
$var wire 32 ' n [31:0] $end
$var wire 1 % start $end
$var wire 1 ! valid $end
$var reg 32 ( f0 [31:0] $end
$var reg 32 ) f1 [31:0] $end
$var reg 32 * fn [31:0] $end
$var reg 32 + n_count [31:0] $end
$upscope $end
$upscope $end
$enddefinitions $end
#0
$dumpvars
b1 +
bx *
b1 )
b0 (
b1010 '
bx &
0%
b1010 $
0#
bx "
0!
$end
#100
b10 +
b1 "
b1 &
b1 *
1%
1#
#200
b1 (
0#
#300
b11 +
b10 "
b10 &
b10 *
1#
#400
b10 )
0#
#500
b100 +
b11 "
b11 &
b11 *
1#
#600
b11 )
b10 (
0#
#700
b101 +
b101 "
b101 &
b101 *
1#
#800
b11 (
b101 )
0#
#900
b110 +
b1000 "
b1000 &
b1000 *
1#
#1000
b1000 )
b101 (
0#
#1100
b111 +
b1101 "
b1101 &
b1101 *
1#
#1200
b1000 (
b1101 )
0#
#1300
b1000 +
b10101 "
b10101 &
b10101 *
1#
#1400
b10101 )
b1101 (
0#
#1500
b1001 +
b100010 "
b100010 &
b100010 *
1#
#1600
b10101 (
b100010 )
0#
#1700
1!
b1010 +
b110111 "
b110111 &
b110111 *
1#
